pipomatic_hudge_xtracta.py
pipomatic_hudge_xtracta-9.2.dist-info/LICENSE
pipomatic_hudge_xtracta-9.2.dist-info/METADATA
pipomatic_hudge_xtracta-9.2.dist-info/WHEEL
pipomatic_hudge_xtracta-9.2.dist-info/top_level.txt
pipomatic_hudge_xtracta-9.2.dist-info/RECORD
