Metadata-Version: 2.1
Name: pipomatic-hudge-xtracta
Version: 9.2
Summary: Xtracta helper file
Home-page: https://github.com/pipomatic_hudge_xtracta
Author: Hudge
Author-email: doug@mybusinessautomated.com
License: UNKNOWN
Platform: UNKNOWN
Classifier: Programming Language :: Python :: 3
Classifier: License :: OSI Approved :: MIT License
Classifier: Operating System :: OS Independent
Requires-Dist: requests
Requires-Dist: xmltodict
Requires-Dist: pandas
Requires-Dist: python-dotenv
Requires-Dist: pillow
Requires-Dist: fuzzywuzzy
Provides-Extra: pl
Requires-Dist: python-Levenshtein ; extra == 'pl'
